scrapy_playfox/__init__.py
scrapy_playfox/handler.py
scrapy_playfox-0.0.1.dist-info/licenses/LICENSE
scrapy_playfox-0.0.1.dist-info/WHEEL
scrapy_playfox-0.0.1.dist-info/METADATA
scrapy_playfox-0.0.1.dist-info/RECORD
