Metadata-Version: 2.4
Name: scrapy-playfox
Version: 0.0.1
Summary: Yet another camoufox integration for scrapy.
License-Expression: Apache-2.0
License-File: LICENSE
Requires-Dist: camoufox[geoip]>=0.4.11
Requires-Dist: scrapy-playwright>=0.0.44
Requires-Python: >=3.13
